{"tasks":[{"id":"1768550192742","name":"每天读书30分钟","type":"DO_WANT","isEnabled":true,"startDate":1768608000000,"endDate":1771200000000,"periodType":"DAILY"},{"id":"1768550972502","name":"每天吃饭一顿","type":"DO_WANT","isEnabled":true,"startDate":1768521600000,"endDate":1771200000000,"periodType":"DAILY"},{"id":"1768551022127","name":"不要喝奶茶","type":"DONT_WANT","isEnabled":true,"startDate":1768521600000,"endDate":1771200000000,"periodType":"DAILY"}],"urgeLogs":[{"id":"1768563842256","timestamp":1768563842256,"assignedIntervention":"BREATHE","isCompleted":false,"outcome":null,"taskId":"1768551022127"},{"id":"1768563794087","timestamp":1768563794087,"assignedIntervention":"DUMP","isCompleted":false,"outcome":null,"taskId":"1768551022127"},{"id":"1768563781665","timestamp":1768563781665,"assignedIntervention":"DUMP","isCompleted":false,"outcome":"resisted","taskId":"1768551022127"},{"id":"1768562921026","timestamp":1768562921026,"assignedIntervention":"BREATHE","isCompleted":false,"outcome":null,"taskId":"1768551022127"},{"id":"1768562662471","timestamp":1768562662471,"assignedIntervention":"DUMP","isCompleted":false,"outcome":null,"taskId":"1768551022127"},{"id":"1768562654256","timestamp":1768562654256,"assignedIntervention":"BREATHE","isCompleted":true,"outcome":null,"taskId":"1768551022127"},{"id":"1768562650472","timestamp":1768562650472,"assignedIntervention":"BREATHE","isCompleted":false,"outcome":null,"taskId":"1768551022127"},{"id":"1768562621937","timestamp":1768562621937,"assignedIntervention":"BREATHE","isCompleted":true,"outcome":null,"taskId":"1768551022127"},{"id":"1768562083667","timestamp":1768562083667,"assignedIntervention":"BREATHE","isCompleted":true,"outcome":null},{"id":"1768561609479","timestamp":1768561609479,"assignedIntervention":"TIMER","isCompleted":true,"outcome":"resisted","taskId":"1768551022127"},{"id":"1768551028873","timestamp":1768551028873,"assignedIntervention":"TIMER","isCompleted":true,"outcome":"resisted","taskId":"1768551022127"},{"id":"1768551025514","timestamp":1768551025514,"assignedIntervention":"DUMP","isCompleted":false,"outcome":null},{"id":"1768550944017","timestamp":1768550944017,"assignedIntervention":"TIMER","isCompleted":false,"outcome":null}],"checkInRecords":[{"id":"1768550982333","taskId":"1768550972502","timestamp":1768550982333,"isCompleted":true,"dateKey":"2026-1-16"}]}